{
"type": "FeatureCollection",
"name": "SWMP_SWMM_storages",
"crs": { "type": "name", "properties": { "name": "urn:ogc:def:crs:OGC:1.3:CRS84" } },
"features": [
{ "type": "Feature", "properties": { "element_ty": "StorageUnit", "id": "BCOM_S100" }, "geometry": { "type": "Point", "coordinates": [ -105.006818110583652, 40.689922777284913 ] } },
{ "type": "Feature", "properties": { "element_ty": "StorageUnit", "id": "BCOM_S975" }, "geometry": { "type": "Point", "coordinates": [ -105.007737352801371, 40.693253554334305 ] } },
{ "type": "Feature", "properties": { "element_ty": "StorageUnit", "id": "BUC_S100" }, "geometry": { "type": "Point", "coordinates": [ -105.010289221609526, 40.711678135123627 ] } },
{ "type": "Feature", "properties": { "element_ty": "StorageUnit", "id": "BUC_S200" }, "geometry": { "type": "Point", "coordinates": [ -105.011176107337263, 40.713865723834523 ] } },
{ "type": "Feature", "properties": { "element_ty": "StorageUnit", "id": "COLE_S100" }, "geometry": { "type": "Point", "coordinates": [ -105.002529836757688, 40.676074548311171 ] } },
{ "type": "Feature", "properties": { "element_ty": "StorageUnit", "id": "CPATM_S100" }, "geometry": { "type": "Point", "coordinates": [ -104.994922198992271, 40.693384726146334 ] } },
{ "type": "Feature", "properties": { "element_ty": "StorageUnit", "id": "KAWS_S100" }, "geometry": { "type": "Point", "coordinates": [ -105.001548285660519, 40.68352037838352 ] } },
{ "type": "Feature", "properties": { "element_ty": "StorageUnit", "id": "KAWS_S150" }, "geometry": { "type": "Point", "coordinates": [ -105.002774229910528, 40.684518811042956 ] } },
{ "type": "Feature", "properties": { "element_ty": "StorageUnit", "id": "KAWS_S200" }, "geometry": { "type": "Point", "coordinates": [ -105.004049296691036, 40.685710214902478 ] } },
{ "type": "Feature", "properties": { "element_ty": "StorageUnit", "id": "KAWS_S250" }, "geometry": { "type": "Point", "coordinates": [ -105.004976207017705, 40.686552068163074 ] } },
{ "type": "Feature", "properties": { "element_ty": "StorageUnit", "id": "KAWS_S350" }, "geometry": { "type": "Point", "coordinates": [ -105.007021329838366, 40.687704162231661 ] } },
{ "type": "Feature", "properties": { "element_ty": "StorageUnit", "id": "KAWS_S500" }, "geometry": { "type": "Point", "coordinates": [ -105.007641261564572, 40.682744775336978 ] } },
{ "type": "Feature", "properties": { "element_ty": "StorageUnit", "id": "KAWS_S750" }, "geometry": { "type": "Point", "coordinates": [ -105.001899164887206, 40.686130822534473 ] } },
{ "type": "Feature", "properties": { "element_ty": "StorageUnit", "id": "MEA_S100" }, "geometry": { "type": "Point", "coordinates": [ -104.992988673348506, 40.682667566094906 ] } },
{ "type": "Feature", "properties": { "element_ty": "StorageUnit", "id": "MEA_S200" }, "geometry": { "type": "Point", "coordinates": [ -104.995825794632694, 40.682818962057993 ] } },
{ "type": "Feature", "properties": { "element_ty": "StorageUnit", "id": "MER_S100" }, "geometry": { "type": "Point", "coordinates": [ -105.018871687453782, 40.704254517884145 ] } },
{ "type": "Feature", "properties": { "element_ty": "StorageUnit", "id": "OLT_S0150" }, "geometry": { "type": "Point", "coordinates": [ -105.001667248865459, 40.696812296499807 ] } },
{ "type": "Feature", "properties": { "element_ty": "StorageUnit", "id": "PAT_S100" }, "geometry": { "type": "Point", "coordinates": [ -105.014643829820614, 40.686370065630385 ] } },
{ "type": "Feature", "properties": { "element_ty": "StorageUnit", "id": "PME_S100" }, "geometry": { "type": "Point", "coordinates": [ -104.991266751904945, 40.690024169188973 ] } },
{ "type": "Feature", "properties": { "element_ty": "StorageUnit", "id": "PME_S200" }, "geometry": { "type": "Point", "coordinates": [ -104.995525959059677, 40.68995378453684 ] } },
{ "type": "Feature", "properties": { "element_ty": "StorageUnit", "id": "SME_S100" }, "geometry": { "type": "Point", "coordinates": [ -105.010778950708271, 40.682815966576143 ] } },
{ "type": "Feature", "properties": { "element_ty": "StorageUnit", "id": "SME_S200" }, "geometry": { "type": "Point", "coordinates": [ -105.010248923890799, 40.689371067039232 ] } },
{ "type": "Feature", "properties": { "element_ty": "StorageUnit", "id": "VPT_S100" }, "geometry": { "type": "Point", "coordinates": [ -105.010095341089993, 40.689998175121438 ] } },
{ "type": "Feature", "properties": { "element_ty": "StorageUnit", "id": "WDO_S100" }, "geometry": { "type": "Point", "coordinates": [ -104.995834829610359, 40.693057714657982 ] } },
{ "type": "Feature", "properties": { "element_ty": "StorageUnit", "id": "WDO_S300" }, "geometry": { "type": "Point", "coordinates": [ -104.999723071076502, 40.693030453125623 ] } },
{ "type": "Feature", "properties": { "element_ty": "StorageUnit", "id": "WPT_S100" }, "geometry": { "type": "Point", "coordinates": [ -105.010710913409184, 40.707078814264904 ] } }
]
}
