{
"type": "FeatureCollection",
"name": "SWMP_SWMM_outfalls",
"crs": { "type": "name", "properties": { "name": "urn:ogc:def:crs:OGC:1.3:CRS84" } },
"features": [
{ "type": "Feature", "properties": { "element_ty": "Outfall", "id": "J7" }, "geometry": { "type": "Point", "coordinates": [ -105.008652661859557, 40.705503340557627 ] } },
{ "type": "Feature", "properties": { "element_ty": "Outfall", "id": "OF1" }, "geometry": { "type": "Point", "coordinates": [ -105.001730776975137, 40.684308912004489 ] } },
{ "type": "Feature", "properties": { "element_ty": "Outfall", "id": "OF10" }, "geometry": { "type": "Point", "coordinates": [ -105.00776501743691, 40.697769426122598 ] } },
{ "type": "Feature", "properties": { "element_ty": "Outfall", "id": "OF11" }, "geometry": { "type": "Point", "coordinates": [ -105.007945864917829, 40.693075044346095 ] } },
{ "type": "Feature", "properties": { "element_ty": "Outfall", "id": "OF12" }, "geometry": { "type": "Point", "coordinates": [ -105.007071961530755, 40.689902381440312 ] } },
{ "type": "Feature", "properties": { "element_ty": "Outfall", "id": "OF13" }, "geometry": { "type": "Point", "coordinates": [ -104.983189815531176, 40.681643970718675 ] } },
{ "type": "Feature", "properties": { "element_ty": "Outfall", "id": "OF14" }, "geometry": { "type": "Point", "coordinates": [ -105.009610634779875, 40.711489139864533 ] } },
{ "type": "Feature", "properties": { "element_ty": "Outfall", "id": "OF15" }, "geometry": { "type": "Point", "coordinates": [ -104.984003955131783, 40.675693598996645 ] } },
{ "type": "Feature", "properties": { "element_ty": "Outfall", "id": "OF16" }, "geometry": { "type": "Point", "coordinates": [ -105.00140271645293, 40.68373081862719 ] } },
{ "type": "Feature", "properties": { "element_ty": "Outfall", "id": "OF17" }, "geometry": { "type": "Point", "coordinates": [ -105.002283410773785, 40.684769188943307 ] } },
{ "type": "Feature", "properties": { "element_ty": "Outfall", "id": "OF18" }, "geometry": { "type": "Point", "coordinates": [ -105.003828858709042, 40.685824112415794 ] } },
{ "type": "Feature", "properties": { "element_ty": "Outfall", "id": "OF19" }, "geometry": { "type": "Point", "coordinates": [ -105.006269915217686, 40.687468141896005 ] } },
{ "type": "Feature", "properties": { "element_ty": "Outfall", "id": "OF2" }, "geometry": { "type": "Point", "coordinates": [ -104.985106556654046, 40.679090586251995 ] } },
{ "type": "Feature", "properties": { "element_ty": "Outfall", "id": "OF20" }, "geometry": { "type": "Point", "coordinates": [ -104.993700189307518, 40.667275549321502 ] } },
{ "type": "Feature", "properties": { "element_ty": "Outfall", "id": "OF21" }, "geometry": { "type": "Point", "coordinates": [ -104.990192712322497, 40.663315052874424 ] } },
{ "type": "Feature", "properties": { "element_ty": "Outfall", "id": "OF22" }, "geometry": { "type": "Point", "coordinates": [ -105.010295945340985, 40.657239225592264 ] } },
{ "type": "Feature", "properties": { "element_ty": "Outfall", "id": "OF23" }, "geometry": { "type": "Point", "coordinates": [ -105.013542909667848, 40.653651454087992 ] } },
{ "type": "Feature", "properties": { "element_ty": "Outfall", "id": "OF24" }, "geometry": { "type": "Point", "coordinates": [ -105.00735749289592, 40.65366167259112 ] } },
{ "type": "Feature", "properties": { "element_ty": "Outfall", "id": "OF25" }, "geometry": { "type": "Point", "coordinates": [ -105.007459257388206, 40.657597105423775 ] } },
{ "type": "Feature", "properties": { "element_ty": "Outfall", "id": "OF3" }, "geometry": { "type": "Point", "coordinates": [ -105.010711508943089, 40.713620434516059 ] } },
{ "type": "Feature", "properties": { "element_ty": "Outfall", "id": "OF4" }, "geometry": { "type": "Point", "coordinates": [ -105.01074079830012, 40.718212115572804 ] } },
{ "type": "Feature", "properties": { "element_ty": "Outfall", "id": "OF5" }, "geometry": { "type": "Point", "coordinates": [ -105.009802495020367, 40.711448028901451 ] } },
{ "type": "Feature", "properties": { "element_ty": "Outfall", "id": "OF6" }, "geometry": { "type": "Point", "coordinates": [ -105.010320403588835, 40.706917660808209 ] } },
{ "type": "Feature", "properties": { "element_ty": "Outfall", "id": "OF7" }, "geometry": { "type": "Point", "coordinates": [ -105.00783395128046, 40.696757206058479 ] } },
{ "type": "Feature", "properties": { "element_ty": "Outfall", "id": "OF8" }, "geometry": { "type": "Point", "coordinates": [ -105.013665580919891, 40.724144283204502 ] } },
{ "type": "Feature", "properties": { "element_ty": "Outfall", "id": "OF9" }, "geometry": { "type": "Point", "coordinates": [ -105.009030443171767, 40.699794405986424 ] } },
{ "type": "Feature", "properties": { "element_ty": "Outfall", "id": "STD504" }, "geometry": { "type": "Point", "coordinates": [ -105.007266662248554, 40.689598139672327 ] } }
]
}
