{
"type": "FeatureCollection",
"name": "mdp_swmm_dividers",
"crs": { "type": "name", "properties": { "name": "urn:ogc:def:crs:OGC:1.3:CRS84" } },
"features": [
{ "type": "Feature", "properties": { "element_ty": "Divider", "id": "90" }, "geometry": { "type": "Point", "coordinates": [ -105.112787385584909, 39.741340498109579 ] } },
{ "type": "Feature", "properties": { "element_ty": "Divider", "id": "110" }, "geometry": { "type": "Point", "coordinates": [ -105.128508837666956, 39.740464517361474 ] } },
{ "type": "Feature", "properties": { "element_ty": "Divider", "id": "111" }, "geometry": { "type": "Point", "coordinates": [ -105.116728189807503, 39.73944668474617 ] } },
{ "type": "Feature", "properties": { "element_ty": "Divider", "id": "114" }, "geometry": { "type": "Point", "coordinates": [ -105.115506584079014, 39.743816947755732 ] } },
{ "type": "Feature", "properties": { "element_ty": "Divider", "id": "115" }, "geometry": { "type": "Point", "coordinates": [ -105.114455996693749, 39.741291426586258 ] } },
{ "type": "Feature", "properties": { "element_ty": "Divider", "id": "115a" }, "geometry": { "type": "Point", "coordinates": [ -105.116756199583051, 39.740456080347087 ] } },
{ "type": "Feature", "properties": { "element_ty": "Divider", "id": "116b" }, "geometry": { "type": "Point", "coordinates": [ -105.1143753938386, 39.738956830813905 ] } },
{ "type": "Feature", "properties": { "element_ty": "Divider", "id": "116c" }, "geometry": { "type": "Point", "coordinates": [ -105.112736167108594, 39.73997709136485 ] } },
{ "type": "Feature", "properties": { "element_ty": "Divider", "id": "117a" }, "geometry": { "type": "Point", "coordinates": [ -105.109745758753249, 39.741584120732334 ] } },
{ "type": "Feature", "properties": { "element_ty": "Divider", "id": "118" }, "geometry": { "type": "Point", "coordinates": [ -105.101613229751536, 39.740379000546781 ] } },
{ "type": "Feature", "properties": { "element_ty": "Divider", "id": "119" }, "geometry": { "type": "Point", "coordinates": [ -105.100423920066305, 39.739902404946314 ] } },
{ "type": "Feature", "properties": { "element_ty": "Divider", "id": "120" }, "geometry": { "type": "Point", "coordinates": [ -105.095682973414725, 39.736352606361258 ] } },
{ "type": "Feature", "properties": { "element_ty": "Divider", "id": "121b" }, "geometry": { "type": "Point", "coordinates": [ -105.090958522356388, 39.736976735583859 ] } },
{ "type": "Feature", "properties": { "element_ty": "Divider", "id": "123" }, "geometry": { "type": "Point", "coordinates": [ -105.082248677217535, 39.735144931434881 ] } },
{ "type": "Feature", "properties": { "element_ty": "Divider", "id": "191" }, "geometry": { "type": "Point", "coordinates": [ -105.109839531196698, 39.739896701965264 ] } },
{ "type": "Feature", "properties": { "element_ty": "Divider", "id": "193" }, "geometry": { "type": "Point", "coordinates": [ -105.080029168500246, 39.733777081186894 ] } },
{ "type": "Feature", "properties": { "element_ty": "Divider", "id": "217" }, "geometry": { "type": "Point", "coordinates": [ -105.105660107087644, 39.741610792291766 ] } },
{ "type": "Feature", "properties": { "element_ty": "Divider", "id": "124" }, "geometry": { "type": "Point", "coordinates": [ -105.081616842690053, 39.734741198713586 ] } }
]
}
