{
"type": "FeatureCollection",
"name": "parcels-fut-mm-cent",
"crs": { "type": "name", "properties": { "name": "urn:ogc:def:crs:OGC:1.3:CRS84" } },
"features": [
{ "type": "Feature", "properties": { "Id": 0, "OWNNAME": "MARTIN MARIETTA" }, "geometry": { "type": "Point", "coordinates": [ -105.213366597372854, 39.706852705080443 ] } },
{ "type": "Feature", "properties": { "Id": 0, "OWNNAME": "MARTIN MARIETTA" }, "geometry": { "type": "Point", "coordinates": [ -105.215986200044469, 39.702497500563084 ] } },
{ "type": "Feature", "properties": { "Id": 0, "OWNNAME": "MARTIN MARIETTA" }, "geometry": { "type": "Point", "coordinates": [ -105.212453119769904, 39.700588718751966 ] } }
]
}
